pyradiobiology/__init__.py
pyradiobiology/models/__init__.py
pyradiobiology/models/geud.py
pyradiobiology/models/linear_quadratic.py
pyradiobiology/models/NTCP/__init__.py
pyradiobiology/models/NTCP/lyman_kutcher_burman.py
pyradiobiology/models/NTCP/relative_seriality.py
pyradiobiology/models/TCP/__init__.py
pyradiobiology/models/TCP/tcp_density.py
pyradiobiology/models/TCP/tcp_empirical.py
pyradiobiology/primitives/__init__.py
pyradiobiology/primitives/dose.py
pyradiobiology/primitives/dose_converter.py
pyradiobiology/primitives/dosebag.py
pyradiobiology-1.0.33.dist-info/LICENSE.txt
pyradiobiology-1.0.33.dist-info/METADATA
pyradiobiology-1.0.33.dist-info/WHEEL
pyradiobiology-1.0.33.dist-info/top_level.txt
pyradiobiology-1.0.33.dist-info/RECORD
